hydrangea/__main__.py
hydrangea-0.1.dist-info/METADATA
hydrangea-0.1.dist-info/WHEEL
hydrangea-0.1.dist-info/entry_points.txt
hydrangea-0.1.dist-info/top_level.txt
hydrangea-0.1.dist-info/RECORD
