Metadata-Version: 2.1
Name: hydrangea
Version: 0.1
Summary: Automate force-directed graph
Home-page: https://github.com/qeeqbox/hydrangea
Author: QeeqBox
Author-email: gigaqeeq@gmail.com
License: AGPL-3.0
Platform: UNKNOWN
Requires-Python: >=3
Requires-Dist: termcolor
